<TRANSFER xmlns="http://www.interlis.ch/INTERLIS2.3">
	<HEADERSECTION SENDER="signedav's lilbulb" VERSION="2.3">
		<MODELS>
			<MODEL NAME="DatasetIdx16" VERSION="2018-11-21" URI="mailto:ce@eisenhutinformatik.ch" />
		</MODELS>
	</HEADERSECTION>
	<DATASECTION>
		<DatasetIdx16.DataIndex BID="dbca8f50-8e39-408a-a0d9-38eccf2e4e85">
			<DatasetIdx16.DataIndex.DatasetMetadata TID="860a66a2-de0b-41fc-8d9d-fda0fc286dcc">
				<id>lg_geolassets_v2.qgis_referenceData_ilidata_bkp</id>
				<version>2022-05-11</version>
				<publishingDate>2022-05-31</publishingDate>
				<owner>mailto:info@swisstopo.ch</owner>
				<title>
					<DatasetIdx16.MultilingualText>
						<LocalisedText>
							<DatasetIdx16.LocalisedText>
								<Text>QGIS referenceData file for lg_geolassets_v2 - ilidata_bkp</Text>
							</DatasetIdx16.LocalisedText>
						</LocalisedText>
					</DatasetIdx16.MultilingualText>
				</title>
				<categories>
					<DatasetIdx16.Code_>
						<value>http://codes.interlis.ch/type/referenceData</value>
					</DatasetIdx16.Code_>
				</categories>
				<files>
					<DatasetIdx16.DataFile>
						<fileFormat>application/xml</fileFormat>
						<file>
							<DatasetIdx16.File>
								<path>./ilidata_bkp.xml</path>
							</DatasetIdx16.File>
						</file>
					</DatasetIdx16.DataFile>
				</files>
			</DatasetIdx16.DataIndex.DatasetMetadata>
			<DatasetIdx16.DataIndex.DatasetMetadata TID="e68d020a-19b5-48d6-9de4-8b8d804f660b">
				<id>lg_geolassets_v2.qgis_metaconfig_lg_geolassets_V2_gpkg</id>
				<version>2022-05-11</version>
				<publishingDate>2022-05-31</publishingDate>
				<owner>mailto:info@swisstopo.ch</owner>
				<title>
					<DatasetIdx16.MultilingualText>
						<LocalisedText>
							<DatasetIdx16.LocalisedText>
								<Text>QGIS metaconfig file for lg_geolassets_v2 - lg_geolassets_V2_gpkg</Text>
							</DatasetIdx16.LocalisedText>
						</LocalisedText>
					</DatasetIdx16.MultilingualText>
				</title>
				<categories>
					<DatasetIdx16.Code_>
						<value>http://codes.interlis.ch/type/metaconfig</value>
					</DatasetIdx16.Code_>
					<DatasetIdx16.Code_>
						<value>http://codes.interlis.ch/model/LG_GeolAssets_V2</value>
					</DatasetIdx16.Code_>
				</categories>
				<files>
					<DatasetIdx16.DataFile>
						<fileFormat>text/plain</fileFormat>
						<file>
							<DatasetIdx16.File>
								<path>./lg_geolassets_v2/metaconfig/lg_geolassets_V2_gpkg.ini</path>
							</DatasetIdx16.File>
						</file>
					</DatasetIdx16.DataFile>
				</files>
			</DatasetIdx16.DataIndex.DatasetMetadata>
			<DatasetIdx16.DataIndex.DatasetMetadata TID="363a13f2-9766-4772-be9b-302e6fd12009">
				<id>lg_geolassets_v2.qgis_referenceData_LG_GeolAssetsCatalogues_V2</id>
				<version>2022-05-11</version>
				<publishingDate>2022-05-31</publishingDate>
				<owner>mailto:info@swisstopo.ch</owner>
				<title>
					<DatasetIdx16.MultilingualText>
						<LocalisedText>
							<DatasetIdx16.LocalisedText>
								<Text>QGIS referenceData file for lg_geolassets_v2 - LG_GeolAssetsCatalogues_V2</Text>
							</DatasetIdx16.LocalisedText>
						</LocalisedText>
					</DatasetIdx16.MultilingualText>
				</title>
				<categories>
					<DatasetIdx16.Code_>
						<value>http://codes.interlis.ch/type/referenceData</value>
					</DatasetIdx16.Code_>
				</categories>
				<files>
					<DatasetIdx16.DataFile>
						<fileFormat>application/xml</fileFormat>
						<file>
							<DatasetIdx16.File>
								<path>./lg_geolassets_v2/referencedata/LG_GeolAssetsCatalogues_V2.xml</path>
							</DatasetIdx16.File>
						</file>
					</DatasetIdx16.DataFile>
				</files>
			</DatasetIdx16.DataIndex.DatasetMetadata>
			<DatasetIdx16.DataIndex.DatasetMetadata TID="35ba0de4-b19f-49fb-a088-4b4ac8ae22d0">
				<id>lg_geolassets_v2.qgis_referenceData_GeolAssetsCatalogues_V2</id>
				<version>2022-05-11</version>
				<publishingDate>2022-05-31</publishingDate>
				<owner>mailto:info@swisstopo.ch</owner>
				<title>
					<DatasetIdx16.MultilingualText>
						<LocalisedText>
							<DatasetIdx16.LocalisedText>
								<Text>QGIS referenceData file for lg_geolassets_v2 - GeolAssetsCatalogues_V2</Text>
							</DatasetIdx16.LocalisedText>
						</LocalisedText>
					</DatasetIdx16.MultilingualText>
				</title>
				<categories>
					<DatasetIdx16.Code_>
						<value>http://codes.interlis.ch/type/referenceData</value>
					</DatasetIdx16.Code_>
				</categories>
				<files>
					<DatasetIdx16.DataFile>
						<fileFormat>application/xml</fileFormat>
						<file>
							<DatasetIdx16.File>
								<path>./lg_geolassets_v2/referencedata/GeolAssetsCatalogues_V2.xml</path>
							</DatasetIdx16.File>
						</file>
					</DatasetIdx16.DataFile>
				</files>
			</DatasetIdx16.DataIndex.DatasetMetadata>
			<DatasetIdx16.DataIndex.DatasetMetadata TID="2b5d53bc-5520-4a54-a2a0-822ddd21610a">
				<id>lg_geolassets_v2.qgis_projecttopping_lg_geolassets_v2_gpkg</id>
				<version>2022-05-11</version>
				<publishingDate>2022-05-31</publishingDate>
				<owner>mailto:info@swisstopo.ch</owner>
				<title>
					<DatasetIdx16.MultilingualText>
						<LocalisedText>
							<DatasetIdx16.LocalisedText>
								<Text>QGIS projecttopping file for lg_geolassets_v2 - lg_geolassets_v2_gpkg</Text>
							</DatasetIdx16.LocalisedText>
						</LocalisedText>
					</DatasetIdx16.MultilingualText>
				</title>
				<categories>
					<DatasetIdx16.Code_>
						<value>http://codes.interlis.ch/type/projecttopping</value>
					</DatasetIdx16.Code_>
				</categories>
				<files>
					<DatasetIdx16.DataFile>
						<fileFormat>text/plain</fileFormat>
						<file>
							<DatasetIdx16.File>
								<path>./lg_geolassets_v2/projecttopping/lg_geolassets_v2_gpkg.yaml</path>
							</DatasetIdx16.File>
						</file>
					</DatasetIdx16.DataFile>
				</files>
			</DatasetIdx16.DataIndex.DatasetMetadata>
			<DatasetIdx16.DataIndex.DatasetMetadata TID="fe7f245d-f77f-4cb6-82a5-630bd80db65a">
				<id>lg_geolassets_v2.qgis_layerstyle_id</id>
				<version>2022-05-11</version>
				<publishingDate>2022-05-31</publishingDate>
				<owner>mailto:info@swisstopo.ch</owner>
				<title>
					<DatasetIdx16.MultilingualText>
						<LocalisedText>
							<DatasetIdx16.LocalisedText>
								<Text>QGIS layerstyle file for lg_geolassets_v2 - id</Text>
							</DatasetIdx16.LocalisedText>
						</LocalisedText>
					</DatasetIdx16.MultilingualText>
				</title>
				<categories>
					<DatasetIdx16.Code_>
						<value>http://codes.interlis.ch/type/layerstyle</value>
					</DatasetIdx16.Code_>
				</categories>
				<files>
					<DatasetIdx16.DataFile>
						<fileFormat>text/plain</fileFormat>
						<file>
							<DatasetIdx16.File>
								<path>./lg_geolassets_v2/layerstyle/id.qml</path>
							</DatasetIdx16.File>
						</file>
					</DatasetIdx16.DataFile>
				</files>
			</DatasetIdx16.DataIndex.DatasetMetadata>
			<DatasetIdx16.DataIndex.DatasetMetadata TID="591bb4bb-9397-419a-9323-251bd0257dcd">
				<id>lg_geolassets_v2.qgis_layerstyle_assetformatitem</id>
				<version>2022-05-11</version>
				<publishingDate>2022-05-31</publishingDate>
				<owner>mailto:info@swisstopo.ch</owner>
				<title>
					<DatasetIdx16.MultilingualText>
						<LocalisedText>
							<DatasetIdx16.LocalisedText>
								<Text>QGIS layerstyle file for lg_geolassets_v2 - assetformatitem</Text>
							</DatasetIdx16.LocalisedText>
						</LocalisedText>
					</DatasetIdx16.MultilingualText>
				</title>
				<categories>
					<DatasetIdx16.Code_>
						<value>http://codes.interlis.ch/type/layerstyle</value>
					</DatasetIdx16.Code_>
				</categories>
				<files>
					<DatasetIdx16.DataFile>
						<fileFormat>text/plain</fileFormat>
						<file>
							<DatasetIdx16.File>
								<path>./lg_geolassets_v2/layerstyle/assetformatitem.qml</path>
							</DatasetIdx16.File>
						</file>
					</DatasetIdx16.DataFile>
				</files>
			</DatasetIdx16.DataIndex.DatasetMetadata>
			<DatasetIdx16.DataIndex.DatasetMetadata TID="30d32fbc-160b-4128-a3f0-858b5be71ee8">
				<id>lg_geolassets_v2.qgis_layerstyle_publication</id>
				<version>2022-05-11</version>
				<publishingDate>2022-05-31</publishingDate>
				<owner>mailto:info@swisstopo.ch</owner>
				<title>
					<DatasetIdx16.MultilingualText>
						<LocalisedText>
							<DatasetIdx16.LocalisedText>
								<Text>QGIS layerstyle file for lg_geolassets_v2 - publication</Text>
							</DatasetIdx16.LocalisedText>
						</LocalisedText>
					</DatasetIdx16.MultilingualText>
				</title>
				<categories>
					<DatasetIdx16.Code_>
						<value>http://codes.interlis.ch/type/layerstyle</value>
					</DatasetIdx16.Code_>
				</categories>
				<files>
					<DatasetIdx16.DataFile>
						<fileFormat>text/plain</fileFormat>
						<file>
							<DatasetIdx16.File>
								<path>./lg_geolassets_v2/layerstyle/publication.qml</path>
							</DatasetIdx16.File>
						</file>
					</DatasetIdx16.DataFile>
				</files>
			</DatasetIdx16.DataIndex.DatasetMetadata>
			<DatasetIdx16.DataIndex.DatasetMetadata TID="c14df906-7746-4a17-8ebb-2c32f2311b3e">
				<id>lg_geolassets_v2.qgis_layerstyle_assetobjectinfo</id>
				<version>2022-05-11</version>
				<publishingDate>2022-05-31</publishingDate>
				<owner>mailto:info@swisstopo.ch</owner>
				<title>
					<DatasetIdx16.MultilingualText>
						<LocalisedText>
							<DatasetIdx16.LocalisedText>
								<Text>QGIS layerstyle file for lg_geolassets_v2 - assetobjectinfo</Text>
							</DatasetIdx16.LocalisedText>
						</LocalisedText>
					</DatasetIdx16.MultilingualText>
				</title>
				<categories>
					<DatasetIdx16.Code_>
						<value>http://codes.interlis.ch/type/layerstyle</value>
					</DatasetIdx16.Code_>
				</categories>
				<files>
					<DatasetIdx16.DataFile>
						<fileFormat>text/plain</fileFormat>
						<file>
							<DatasetIdx16.File>
								<path>./lg_geolassets_v2/layerstyle/assetobjectinfo.qml</path>
							</DatasetIdx16.File>
						</file>
					</DatasetIdx16.DataFile>
				</files>
			</DatasetIdx16.DataIndex.DatasetMetadata>
			<DatasetIdx16.DataIndex.DatasetMetadata TID="80370a87-8833-4293-992d-905b9079ceb7">
				<id>lg_geolassets_v2.qgis_layerstyle_legaldoc</id>
				<version>2022-05-11</version>
				<publishingDate>2022-05-31</publishingDate>
				<owner>mailto:info@swisstopo.ch</owner>
				<title>
					<DatasetIdx16.MultilingualText>
						<LocalisedText>
							<DatasetIdx16.LocalisedText>
								<Text>QGIS layerstyle file for lg_geolassets_v2 - legaldoc</Text>
							</DatasetIdx16.LocalisedText>
						</LocalisedText>
					</DatasetIdx16.MultilingualText>
				</title>
				<categories>
					<DatasetIdx16.Code_>
						<value>http://codes.interlis.ch/type/layerstyle</value>
					</DatasetIdx16.Code_>
				</categories>
				<files>
					<DatasetIdx16.DataFile>
						<fileFormat>text/plain</fileFormat>
						<file>
							<DatasetIdx16.File>
								<path>./lg_geolassets_v2/layerstyle/legaldoc.qml</path>
							</DatasetIdx16.File>
						</file>
					</DatasetIdx16.DataFile>
				</files>
			</DatasetIdx16.DataIndex.DatasetMetadata>
			<DatasetIdx16.DataIndex.DatasetMetadata TID="58c96c9f-6661-4542-a9b2-818e13b1ed17">
				<id>lg_geolassets_v2.qgis_layerstyle_address</id>
				<version>2022-05-11</version>
				<publishingDate>2022-05-31</publishingDate>
				<owner>mailto:info@swisstopo.ch</owner>
				<title>
					<DatasetIdx16.MultilingualText>
						<LocalisedText>
							<DatasetIdx16.LocalisedText>
								<Text>QGIS layerstyle file for lg_geolassets_v2 - address</Text>
							</DatasetIdx16.LocalisedText>
						</LocalisedText>
					</DatasetIdx16.MultilingualText>
				</title>
				<categories>
					<DatasetIdx16.Code_>
						<value>http://codes.interlis.ch/type/layerstyle</value>
					</DatasetIdx16.Code_>
				</categories>
				<files>
					<DatasetIdx16.DataFile>
						<fileFormat>text/plain</fileFormat>
						<file>
							<DatasetIdx16.File>
								<path>./lg_geolassets_v2/layerstyle/address.qml</path>
							</DatasetIdx16.File>
						</file>
					</DatasetIdx16.DataFile>
				</files>
			</DatasetIdx16.DataIndex.DatasetMetadata>
			<DatasetIdx16.DataIndex.DatasetMetadata TID="7928ae00-418a-49cf-9e5e-f31afc2c1377">
				<id>lg_geolassets_v2.qgis_layerstyle_mancatlabelitem</id>
				<version>2022-05-11</version>
				<publishingDate>2022-05-31</publishingDate>
				<owner>mailto:info@swisstopo.ch</owner>
				<title>
					<DatasetIdx16.MultilingualText>
						<LocalisedText>
							<DatasetIdx16.LocalisedText>
								<Text>QGIS layerstyle file for lg_geolassets_v2 - mancatlabelitem</Text>
							</DatasetIdx16.LocalisedText>
						</LocalisedText>
					</DatasetIdx16.MultilingualText>
				</title>
				<categories>
					<DatasetIdx16.Code_>
						<value>http://codes.interlis.ch/type/layerstyle</value>
					</DatasetIdx16.Code_>
				</categories>
				<files>
					<DatasetIdx16.DataFile>
						<fileFormat>text/plain</fileFormat>
						<file>
							<DatasetIdx16.File>
								<path>./lg_geolassets_v2/layerstyle/mancatlabelitem.qml</path>
							</DatasetIdx16.File>
						</file>
					</DatasetIdx16.DataFile>
				</files>
			</DatasetIdx16.DataIndex.DatasetMetadata>
			<DatasetIdx16.DataIndex.DatasetMetadata TID="6a3b26e1-2a4b-4926-9e89-05744800f3ce">
				<id>lg_geolassets_v2.qgis_layerstyle_studyarea</id>
				<version>2022-05-11</version>
				<publishingDate>2022-05-31</publishingDate>
				<owner>mailto:info@swisstopo.ch</owner>
				<title>
					<DatasetIdx16.MultilingualText>
						<LocalisedText>
							<DatasetIdx16.LocalisedText>
								<Text>QGIS layerstyle file for lg_geolassets_v2 - studyarea</Text>
							</DatasetIdx16.LocalisedText>
						</LocalisedText>
					</DatasetIdx16.MultilingualText>
				</title>
				<categories>
					<DatasetIdx16.Code_>
						<value>http://codes.interlis.ch/type/layerstyle</value>
					</DatasetIdx16.Code_>
				</categories>
				<files>
					<DatasetIdx16.DataFile>
						<fileFormat>text/plain</fileFormat>
						<file>
							<DatasetIdx16.File>
								<path>./lg_geolassets_v2/layerstyle/studyarea.qml</path>
							</DatasetIdx16.File>
						</file>
					</DatasetIdx16.DataFile>
				</files>
			</DatasetIdx16.DataIndex.DatasetMetadata>
			<DatasetIdx16.DataIndex.DatasetMetadata TID="51901009-95ca-4311-9b64-903036bc34ea">
				<id>lg_geolassets_v2.qgis_layerstyle_internaluse</id>
				<version>2022-05-11</version>
				<publishingDate>2022-05-31</publishingDate>
				<owner>mailto:info@swisstopo.ch</owner>
				<title>
					<DatasetIdx16.MultilingualText>
						<LocalisedText>
							<DatasetIdx16.LocalisedText>
								<Text>QGIS layerstyle file for lg_geolassets_v2 - internaluse</Text>
							</DatasetIdx16.LocalisedText>
						</LocalisedText>
					</DatasetIdx16.MultilingualText>
				</title>
				<categories>
					<DatasetIdx16.Code_>
						<value>http://codes.interlis.ch/type/layerstyle</value>
					</DatasetIdx16.Code_>
				</categories>
				<files>
					<DatasetIdx16.DataFile>
						<fileFormat>text/plain</fileFormat>
						<file>
							<DatasetIdx16.File>
								<path>./lg_geolassets_v2/layerstyle/internaluse.qml</path>
							</DatasetIdx16.File>
						</file>
					</DatasetIdx16.DataFile>
				</files>
			</DatasetIdx16.DataIndex.DatasetMetadata>
			<DatasetIdx16.DataIndex.DatasetMetadata TID="1076afeb-c948-46a0-9005-ac3eae32b20f">
				<id>lg_geolassets_v2.qgis_layerstyle_contact</id>
				<version>2022-05-11</version>
				<publishingDate>2022-05-31</publishingDate>
				<owner>mailto:info@swisstopo.ch</owner>
				<title>
					<DatasetIdx16.MultilingualText>
						<LocalisedText>
							<DatasetIdx16.LocalisedText>
								<Text>QGIS layerstyle file for lg_geolassets_v2 - contact</Text>
							</DatasetIdx16.LocalisedText>
						</LocalisedText>
					</DatasetIdx16.MultilingualText>
				</title>
				<categories>
					<DatasetIdx16.Code_>
						<value>http://codes.interlis.ch/type/layerstyle</value>
					</DatasetIdx16.Code_>
				</categories>
				<files>
					<DatasetIdx16.DataFile>
						<fileFormat>text/plain</fileFormat>
						<file>
							<DatasetIdx16.File>
								<path>./lg_geolassets_v2/layerstyle/contact.qml</path>
							</DatasetIdx16.File>
						</file>
					</DatasetIdx16.DataFile>
				</files>
			</DatasetIdx16.DataIndex.DatasetMetadata>
			<DatasetIdx16.DataIndex.DatasetMetadata TID="d39f17bf-318a-40b7-821b-4d4767de1f95">
				<id>lg_geolassets_v2.qgis_layerstyle_assetitem</id>
				<version>2022-05-11</version>
				<publishingDate>2022-05-31</publishingDate>
				<owner>mailto:info@swisstopo.ch</owner>
				<title>
					<DatasetIdx16.MultilingualText>
						<LocalisedText>
							<DatasetIdx16.LocalisedText>
								<Text>QGIS layerstyle file for lg_geolassets_v2 - assetitem</Text>
							</DatasetIdx16.LocalisedText>
						</LocalisedText>
					</DatasetIdx16.MultilingualText>
				</title>
				<categories>
					<DatasetIdx16.Code_>
						<value>http://codes.interlis.ch/type/layerstyle</value>
					</DatasetIdx16.Code_>
				</categories>
				<files>
					<DatasetIdx16.DataFile>
						<fileFormat>text/plain</fileFormat>
						<file>
							<DatasetIdx16.File>
								<path>./lg_geolassets_v2/layerstyle/assetitem.qml</path>
							</DatasetIdx16.File>
						</file>
					</DatasetIdx16.DataFile>
				</files>
			</DatasetIdx16.DataIndex.DatasetMetadata>
			<DatasetIdx16.DataIndex.DatasetMetadata TID="db62a754-909f-452e-bab1-55db303d7e64">
				<id>lg_geolassets_v2.qgis_layerstyle_statuswork</id>
				<version>2022-05-11</version>
				<publishingDate>2022-05-31</publishingDate>
				<owner>mailto:info@swisstopo.ch</owner>
				<title>
					<DatasetIdx16.MultilingualText>
						<LocalisedText>
							<DatasetIdx16.LocalisedText>
								<Text>QGIS layerstyle file for lg_geolassets_v2 - statuswork</Text>
							</DatasetIdx16.LocalisedText>
						</LocalisedText>
					</DatasetIdx16.MultilingualText>
				</title>
				<categories>
					<DatasetIdx16.Code_>
						<value>http://codes.interlis.ch/type/layerstyle</value>
					</DatasetIdx16.Code_>
				</categories>
				<files>
					<DatasetIdx16.DataFile>
						<fileFormat>text/plain</fileFormat>
						<file>
							<DatasetIdx16.File>
								<path>./lg_geolassets_v2/layerstyle/statuswork.qml</path>
							</DatasetIdx16.File>
						</file>
					</DatasetIdx16.DataFile>
				</files>
			</DatasetIdx16.DataIndex.DatasetMetadata>
			<DatasetIdx16.DataIndex.DatasetMetadata TID="1f795e54-d37a-454f-be5a-f2b676b45296">
				<id>lg_geolassets_v2.qgis_layerstyle_autocat</id>
				<version>2022-05-11</version>
				<publishingDate>2022-05-31</publishingDate>
				<owner>mailto:info@swisstopo.ch</owner>
				<title>
					<DatasetIdx16.MultilingualText>
						<LocalisedText>
							<DatasetIdx16.LocalisedText>
								<Text>QGIS layerstyle file for lg_geolassets_v2 - autocat</Text>
							</DatasetIdx16.LocalisedText>
						</LocalisedText>
					</DatasetIdx16.MultilingualText>
				</title>
				<categories>
					<DatasetIdx16.Code_>
						<value>http://codes.interlis.ch/type/layerstyle</value>
					</DatasetIdx16.Code_>
				</categories>
				<files>
					<DatasetIdx16.DataFile>
						<fileFormat>text/plain</fileFormat>
						<file>
							<DatasetIdx16.File>
								<path>./lg_geolassets_v2/layerstyle/autocat.qml</path>
							</DatasetIdx16.File>
						</file>
					</DatasetIdx16.DataFile>
				</files>
			</DatasetIdx16.DataIndex.DatasetMetadata>
			<DatasetIdx16.DataIndex.DatasetMetadata TID="37c130d7-bf98-4477-a6d2-2c13261a3dad">
				<id>lg_geolassets_v2.qgis_layerstyle_assetkinditem</id>
				<version>2022-05-11</version>
				<publishingDate>2022-05-31</publishingDate>
				<owner>mailto:info@swisstopo.ch</owner>
				<title>
					<DatasetIdx16.MultilingualText>
						<LocalisedText>
							<DatasetIdx16.LocalisedText>
								<Text>QGIS layerstyle file for lg_geolassets_v2 - assetkinditem</Text>
							</DatasetIdx16.LocalisedText>
						</LocalisedText>
					</DatasetIdx16.MultilingualText>
				</title>
				<categories>
					<DatasetIdx16.Code_>
						<value>http://codes.interlis.ch/type/layerstyle</value>
					</DatasetIdx16.Code_>
				</categories>
				<files>
					<DatasetIdx16.DataFile>
						<fileFormat>text/plain</fileFormat>
						<file>
							<DatasetIdx16.File>
								<path>./lg_geolassets_v2/layerstyle/assetkinditem.qml</path>
							</DatasetIdx16.File>
						</file>
					</DatasetIdx16.DataFile>
				</files>
			</DatasetIdx16.DataIndex.DatasetMetadata>
			<DatasetIdx16.DataIndex.DatasetMetadata TID="affb2104-89e5-4778-9e48-4f4121ff5065">
				<id>lg_geolassets_v2.qgis_layerstyle_statusworkitem</id>
				<version>2022-05-11</version>
				<publishingDate>2022-05-31</publishingDate>
				<owner>mailto:info@swisstopo.ch</owner>
				<title>
					<DatasetIdx16.MultilingualText>
						<LocalisedText>
							<DatasetIdx16.LocalisedText>
								<Text>QGIS layerstyle file for lg_geolassets_v2 - statusworkitem</Text>
							</DatasetIdx16.LocalisedText>
						</LocalisedText>
					</DatasetIdx16.MultilingualText>
				</title>
				<categories>
					<DatasetIdx16.Code_>
						<value>http://codes.interlis.ch/type/layerstyle</value>
					</DatasetIdx16.Code_>
				</categories>
				<files>
					<DatasetIdx16.DataFile>
						<fileFormat>text/plain</fileFormat>
						<file>
							<DatasetIdx16.File>
								<path>./lg_geolassets_v2/layerstyle/statusworkitem.qml</path>
							</DatasetIdx16.File>
						</file>
					</DatasetIdx16.DataFile>
				</files>
			</DatasetIdx16.DataIndex.DatasetMetadata>
			<DatasetIdx16.DataIndex.DatasetMetadata TID="3db061d9-9415-405d-a6e6-c3ced456f427">
				<id>lg_geolassets_v2.qgis_layerstyle_typenatrel</id>
				<version>2022-05-11</version>
				<publishingDate>2022-05-31</publishingDate>
				<owner>mailto:info@swisstopo.ch</owner>
				<title>
					<DatasetIdx16.MultilingualText>
						<LocalisedText>
							<DatasetIdx16.LocalisedText>
								<Text>QGIS layerstyle file for lg_geolassets_v2 - typenatrel</Text>
							</DatasetIdx16.LocalisedText>
						</LocalisedText>
					</DatasetIdx16.MultilingualText>
				</title>
				<categories>
					<DatasetIdx16.Code_>
						<value>http://codes.interlis.ch/type/layerstyle</value>
					</DatasetIdx16.Code_>
				</categories>
				<files>
					<DatasetIdx16.DataFile>
						<fileFormat>text/plain</fileFormat>
						<file>
							<DatasetIdx16.File>
								<path>./lg_geolassets_v2/layerstyle/typenatrel.qml</path>
							</DatasetIdx16.File>
						</file>
					</DatasetIdx16.DataFile>
				</files>
			</DatasetIdx16.DataIndex.DatasetMetadata>
			<DatasetIdx16.DataIndex.DatasetMetadata TID="1584e539-2043-4ff2-becc-e4a15b43c5c2">
				<id>lg_geolassets_v2.qgis_layerstyle_natrelitem</id>
				<version>2022-05-11</version>
				<publishingDate>2022-05-31</publishingDate>
				<owner>mailto:info@swisstopo.ch</owner>
				<title>
					<DatasetIdx16.MultilingualText>
						<LocalisedText>
							<DatasetIdx16.LocalisedText>
								<Text>QGIS layerstyle file for lg_geolassets_v2 - natrelitem</Text>
							</DatasetIdx16.LocalisedText>
						</LocalisedText>
					</DatasetIdx16.MultilingualText>
				</title>
				<categories>
					<DatasetIdx16.Code_>
						<value>http://codes.interlis.ch/type/layerstyle</value>
					</DatasetIdx16.Code_>
				</categories>
				<files>
					<DatasetIdx16.DataFile>
						<fileFormat>text/plain</fileFormat>
						<file>
							<DatasetIdx16.File>
								<path>./lg_geolassets_v2/layerstyle/natrelitem.qml</path>
							</DatasetIdx16.File>
						</file>
					</DatasetIdx16.DataFile>
				</files>
			</DatasetIdx16.DataIndex.DatasetMetadata>
			<DatasetIdx16.DataIndex.DatasetMetadata TID="7d9e8828-5a6f-44e0-b2ae-9a7c34ee25fc">
				<id>lg_geolassets_v2.qgis_layerstyle_internalproject</id>
				<version>2022-05-11</version>
				<publishingDate>2022-05-31</publishingDate>
				<owner>mailto:info@swisstopo.ch</owner>
				<title>
					<DatasetIdx16.MultilingualText>
						<LocalisedText>
							<DatasetIdx16.LocalisedText>
								<Text>QGIS layerstyle file for lg_geolassets_v2 - internalproject</Text>
							</DatasetIdx16.LocalisedText>
						</LocalisedText>
					</DatasetIdx16.MultilingualText>
				</title>
				<categories>
					<DatasetIdx16.Code_>
						<value>http://codes.interlis.ch/type/layerstyle</value>
					</DatasetIdx16.Code_>
				</categories>
				<files>
					<DatasetIdx16.DataFile>
						<fileFormat>text/plain</fileFormat>
						<file>
							<DatasetIdx16.File>
								<path>./lg_geolassets_v2/layerstyle/internalproject.qml</path>
							</DatasetIdx16.File>
						</file>
					</DatasetIdx16.DataFile>
				</files>
			</DatasetIdx16.DataIndex.DatasetMetadata>
			<DatasetIdx16.DataIndex.DatasetMetadata TID="d6ac388c-29d4-489c-907b-43e97b4a0f3f">
				<id>lg_geolassets_v2.qgis_layerstyle_publicuse</id>
				<version>2022-05-11</version>
				<publishingDate>2022-05-31</publishingDate>
				<owner>mailto:info@swisstopo.ch</owner>
				<title>
					<DatasetIdx16.MultilingualText>
						<LocalisedText>
							<DatasetIdx16.LocalisedText>
								<Text>QGIS layerstyle file for lg_geolassets_v2 - publicuse</Text>
							</DatasetIdx16.LocalisedText>
						</LocalisedText>
					</DatasetIdx16.MultilingualText>
				</title>
				<categories>
					<DatasetIdx16.Code_>
						<value>http://codes.interlis.ch/type/layerstyle</value>
					</DatasetIdx16.Code_>
				</categories>
				<files>
					<DatasetIdx16.DataFile>
						<fileFormat>text/plain</fileFormat>
						<file>
							<DatasetIdx16.File>
								<path>./lg_geolassets_v2/layerstyle/publicuse.qml</path>
							</DatasetIdx16.File>
						</file>
					</DatasetIdx16.DataFile>
				</files>
			</DatasetIdx16.DataIndex.DatasetMetadata>
			<DatasetIdx16.DataIndex.DatasetMetadata TID="da27f871-b226-4ad0-a12e-570b6beee192">
				<id>lg_geolassets_v2.qgis_layerstyle_studylocation</id>
				<version>2022-05-11</version>
				<publishingDate>2022-05-31</publishingDate>
				<owner>mailto:info@swisstopo.ch</owner>
				<title>
					<DatasetIdx16.MultilingualText>
						<LocalisedText>
							<DatasetIdx16.LocalisedText>
								<Text>QGIS layerstyle file for lg_geolassets_v2 - studylocation</Text>
							</DatasetIdx16.LocalisedText>
						</LocalisedText>
					</DatasetIdx16.MultilingualText>
				</title>
				<categories>
					<DatasetIdx16.Code_>
						<value>http://codes.interlis.ch/type/layerstyle</value>
					</DatasetIdx16.Code_>
				</categories>
				<files>
					<DatasetIdx16.DataFile>
						<fileFormat>text/plain</fileFormat>
						<file>
							<DatasetIdx16.File>
								<path>./lg_geolassets_v2/layerstyle/studylocation.qml</path>
							</DatasetIdx16.File>
						</file>
					</DatasetIdx16.DataFile>
				</files>
			</DatasetIdx16.DataIndex.DatasetMetadata>
			<DatasetIdx16.DataIndex.DatasetMetadata TID="03c8cd16-4781-4ff7-a16a-8060cea8a3c8">
				<id>lg_geolassets_v2.qgis_layerstyle_studytrace</id>
				<version>2022-05-11</version>
				<publishingDate>2022-05-31</publishingDate>
				<owner>mailto:info@swisstopo.ch</owner>
				<title>
					<DatasetIdx16.MultilingualText>
						<LocalisedText>
							<DatasetIdx16.LocalisedText>
								<Text>QGIS layerstyle file for lg_geolassets_v2 - studytrace</Text>
							</DatasetIdx16.LocalisedText>
						</LocalisedText>
					</DatasetIdx16.MultilingualText>
				</title>
				<categories>
					<DatasetIdx16.Code_>
						<value>http://codes.interlis.ch/type/layerstyle</value>
					</DatasetIdx16.Code_>
				</categories>
				<files>
					<DatasetIdx16.DataFile>
						<fileFormat>text/plain</fileFormat>
						<file>
							<DatasetIdx16.File>
								<path>./lg_geolassets_v2/layerstyle/studytrace.qml</path>
							</DatasetIdx16.File>
						</file>
					</DatasetIdx16.DataFile>
				</files>
			</DatasetIdx16.DataIndex.DatasetMetadata>
			<DatasetIdx16.DataIndex.DatasetMetadata TID="0270cafe-43c9-495b-8e82-09de99a84549">
				<id>lg_geolassets_v2.qgis_layerdefinition_hintergrundkarten</id>
				<version>2022-05-11</version>
				<publishingDate>2022-05-31</publishingDate>
				<owner>mailto:info@swisstopo.ch</owner>
				<title>
					<DatasetIdx16.MultilingualText>
						<LocalisedText>
							<DatasetIdx16.LocalisedText>
								<Text>QGIS layerdefinition file for lg_geolassets_v2 - hintergrundkarten</Text>
							</DatasetIdx16.LocalisedText>
						</LocalisedText>
					</DatasetIdx16.MultilingualText>
				</title>
				<categories>
					<DatasetIdx16.Code_>
						<value>http://codes.interlis.ch/type/layerdefinition</value>
					</DatasetIdx16.Code_>
					<DatasetIdx16.Code_>
						<value>http://codes.interlis.ch/model/LG_GeolAssets_V2</value>
					</DatasetIdx16.Code_>
				</categories>
				<files>
					<DatasetIdx16.DataFile>
						<fileFormat>text/plain</fileFormat>
						<file>
							<DatasetIdx16.File>
								<path>./lg_geolassets_v2/layerdefinition/hintergrundkarten.qlr</path>
							</DatasetIdx16.File>
						</file>
					</DatasetIdx16.DataFile>
				</files>
			</DatasetIdx16.DataIndex.DatasetMetadata>
		</DatasetIdx16.DataIndex>
	</DATASECTION>
</TRANSFER>